{
  "routes": [
    {
      "method": "GET",
      "path": "/user-contacts",
      "handler": "user-contact.find",
      "config": {
        "policies": []
      }
    },
    {
      "method": "GET",
      "path": "/user-contacts/count",
      "handler": "user-contact.count",
      "config": {
        "policies": []
      }
    },
    {
      "method": "GET",
      "path": "/user-contacts/:id",
      "handler": "user-contact.findOne",
      "config": {
        "policies": []
      }
    },
    {
      "method": "POST",
      "path": "/user-contacts",
      "handler": "user-contact.create",
      "config": {
        "policies": []
      }
    },
    {
      "method": "PUT",
      "path": "/user-contacts/:id",
      "handler": "user-contact.update",
      "config": {
        "policies": []
      }
    },
    {
      "method": "DELETE",
      "path": "/user-contacts/:id",
      "handler": "user-contact.delete",
      "config": {
        "policies": []
      }
    }
  ]
}
